powerview/__init__.py
powerview/_version.py
powerview/powerview.py
powerview/lib/__init__.py
powerview/lib/dfsnm.py
powerview/lib/dns.py
powerview/lib/reg.py
powerview/lib/resolver.py
powerview/lib/samr.py
powerview/lib/tsts.py
powerview/lib/adws/__init__.py
powerview/lib/adws/error.py
powerview/lib/adws/nmf.py
powerview/lib/adws/nns.py
powerview/lib/adws/core/__init__.py
powerview/lib/adws/core/connection.py
powerview/lib/adws/core/server.py
powerview/lib/adws/encoder/__init__.py
powerview/lib/adws/encoder/encoder.py
powerview/lib/adws/encoder/xml_parser.py
powerview/lib/adws/encoder/records/__init__.py
powerview/lib/adws/encoder/records/attributes.py
powerview/lib/adws/encoder/records/constants.py
powerview/lib/adws/encoder/records/datatypes.py
powerview/lib/adws/encoder/records/elements.py
powerview/lib/adws/encoder/records/record.py
powerview/lib/adws/encoder/records/text.py
powerview/lib/adws/encoder/records/utils.py
powerview/lib/adws/extend/standard/PagedSearch.py
powerview/lib/adws/extend/standard/__init__.py
powerview/lib/adws/operation/add.py
powerview/lib/adws/operation/delete.py
powerview/lib/adws/operation/modify.py
powerview/lib/adws/operation/modifyDN.py
powerview/lib/adws/operation/search.py
powerview/lib/adws/templates/__init__.py
powerview/lib/krb5/asn1.py
powerview/lib/krb5/constants.py
powerview/lib/krb5/kerberosv5.py
powerview/lib/ldap3/extend/__init__.py
powerview/lib/ldap3/extend/obfuscate/__init__.py
powerview/lib/ldap3/extend/obfuscate/core/__init__.py
powerview/lib/ldap3/extend/obfuscate/core/constants.py
powerview/lib/ldap3/extend/obfuscate/core/exceptions.py
powerview/lib/ldap3/extend/obfuscate/core/parsers.py
powerview/lib/ldap3/extend/obfuscate/strategies/__init__.py
powerview/lib/ldap3/extend/obfuscate/strategies/attribute_obfuscation.py
powerview/lib/ldap3/extend/obfuscate/strategies/operator_obfuscation.py
powerview/lib/ldap3/extend/obfuscate/strategies/value_obfuscation.py
powerview-2025.1.6.dist-info/licenses/LICENSE
powerview-2025.1.6.dist-info/METADATA
powerview-2025.1.6.dist-info/WHEEL
powerview-2025.1.6.dist-info/entry_points.txt
powerview-2025.1.6.dist-info/top_level.txt
powerview-2025.1.6.dist-info/RECORD
