Metadata-Version: 2.4
Name: powerview
Version: 2025.1.6
Summary: Python based PowerView script
Author-email: Aniq Fakhrul <aniqfakhrull@gmail.com>
License-Expression: MIT
Project-URL: homepage, https://github.com/aniqfakhrul/powerview.py
Project-URL: repository, https://github.com/aniqfakhrul/powerview.py
Classifier: Intended Audience :: Information Technology
Classifier: Programming Language :: Python :: 3.5
Classifier: Programming Language :: Python :: 3.6
Classifier: Programming Language :: Python :: 3.7
Classifier: Programming Language :: Python :: 3.8
Classifier: Programming Language :: Python :: 3.9
Classifier: Programming Language :: Python :: 3.10
Classifier: Programming Language :: Python :: 3.11
Classifier: Programming Language :: Python :: 3.12
License-File: LICENSE
Requires-Dist: ldap3-bleeding-edge
Requires-Dist: impacket
Requires-Dist: dnspython
Requires-Dist: future
Requires-Dist: gnureadline
Requires-Dist: validators
Requires-Dist: dsinternals
Requires-Dist: chardet
Requires-Dist: tabulate
Requires-Dist: argparse
Requires-Dist: requests_ntlm
Requires-Dist: python-dateutil
Requires-Dist: flask
Requires-Dist: flask-basicauth
Requires-Dist: pycryptodome
Requires-Dist: fastmcp
Provides-Extra: mcp
Requires-Dist: fastmcp; extra == "mcp"
Dynamic: license-file
